{
  "Id": "d238f638-4f1f-4df3-b7ad-29257a30607b",
  "Name": "AppointmentAccessor",
  "OriginalName": "AppointmentAccessor",
  "NamePlural": "AppointmentAccessors",
  "DatabaseTableName": "AppointmentAccessors",
  "Namespace": "AppointmentAccessors",
  "Type": 1,
  "MasterEntityName": null,
  "MasterEntity": null,
  "BaseClass": "FullAuditedEntity",
  "PageTitle": "AppointmentAccessors",
  "MenuIcon": "file-alt",
  "PrimaryKeyType": "Guid",
  "PreserveCustomCode": false,
  "IsMultiTenant": true,
  "CheckConcurrency": false,
  "BulkDeleteEnabled": false,
  "ShouldCreateUserInterface": false,
  "ShouldCreateBackend": true,
  "ShouldExportExcel": false,
  "ShouldAddMigration": false,
  "ShouldUpdateDatabase": false,
  "CreateTests": false,
  "Properties": [
    {
      "Id": "5d3c8422-91e1-4622-aa25-a2c4feaf7443",
      "Name": "AccessTypeId",
      "Type": "enum",
      "EnumType": "AccessType",
      "EnumNamespace": "HealthcareSupport.CaseEvaluation.Enums",
      "EnumAngularImport": "shared/enums/access-type",
      "EnumFilePath": "/src/HealthcareSupport.CaseEvaluation.Domain.Shared/Enums/AccessType.cs",
      "DefaultValue": null,
      "IsNullable": false,
      "IsRequired": false,
      "IsFilterable": true,
      "AllowEmptyStrings": false,
      "IsTextArea": false,
      "MinLength": null,
      "MaxLength": null,
      "SortOrder": 0,
      "SortType": 0,
      "Regex": "",
      "EmailValidation": false,
      "ShowOnList": true,
      "ShowOnCreateModal": true,
      "ShowOnEditModal": true,
      "ReadonlyOnEditModal": false,
      "EnumValues": {
        "View": 23,
        "Edit": 24
      },
      "IsSelected": true,
      "MaxFileSize": null,
      "OrdinalIndex": 0
    }
  ],
  "NavigationProperties": [
    {
      "EntityNameWithDuplicationNumber": "IdentityUser",
      "EntitySetNameWithDuplicationNumber": "IdentityUsers",
      "ReferencePropertyName": "IdentityUser",
      "UiPickType": "Dropdown",
      "IsRequired": true,
      "IncludeEntitiesFromModules": true,
      "FromAbpModule": true,
      "Name": "IdentityUserId",
      "DisplayProperty": "Email",
      "Namespace": "Volo.Abp.Identity",
      "EntityName": "IdentityUser",
      "EntitySetName": "IdentityUsers",
      "DtoNamespace": "Volo.Abp.Identity",
      "DtoEntityName": "IdentityUserDto",
      "Type": "Guid",
      "IsFilterable": true
    },
    {
      "EntityNameWithDuplicationNumber": "Appointment",
      "EntitySetNameWithDuplicationNumber": "Appointments",
      "ReferencePropertyName": "Appointment",
      "UiPickType": "Dropdown",
      "IsRequired": true,
      "IncludeEntitiesFromModules": false,
      "FromAbpModule": false,
      "Name": "AppointmentId",
      "DisplayProperty": "RequestConfirmationNumber",
      "Namespace": "HealthcareSupport.CaseEvaluation.Appointments",
      "EntityName": "Appointment",
      "EntitySetName": "Appointments",
      "DtoNamespace": "HealthcareSupport.CaseEvaluation.Appointments",
      "DtoEntityName": "AppointmentDto",
      "Type": "Guid",
      "IsFilterable": true
    }
  ],
  "NavigationConnections": [],
  "ChildEntities": [],
  "PhysicalFileName": "AppointmentAccessor.json"
}